c2md/__init__.py
c2md/__main__.py
c2md/file_organizer.py
c2md/index_generator.py
c2md/markdown_writer.py
c2md/parser.py
c2md/url_mapper.py
c2md-1.1.1.dist-info/METADATA
c2md-1.1.1.dist-info/WHEEL
c2md-1.1.1.dist-info/entry_points.txt
c2md-1.1.1.dist-info/licenses/LICENSE
c2md-1.1.1.dist-info/RECORD
