Metadata-Version: 2.4
Name: c2md
Version: 1.1.1
Summary: Tool to convert Context7 formatted llms.txt to locally organized markdown library documentation
Project-URL: Homepage, https://github.com/crisp-sh/context7-to-markdown
Project-URL: Bug Reports, https://github.com/crisp-sh/context7-to-markdown/issues
Project-URL: Source, https://github.com/crisp-sh/context7-to-markdown
Author-email: crisp-sh <s@crisp.sh>
License: MIT
License-File: LICENSE
Keywords: cli,context7,converter,documentation,markdown
Classifier: Development Status :: 4 - Beta
Classifier: Intended Audience :: Developers
Classifier: License :: OSI Approved :: MIT License
Classifier: Operating System :: OS Independent
Classifier: Programming Language :: Python :: 3
Classifier: Programming Language :: Python :: 3.8
Classifier: Programming Language :: Python :: 3.9
Classifier: Programming Language :: Python :: 3.10
Classifier: Programming Language :: Python :: 3.11
Classifier: Programming Language :: Python :: 3.12
Classifier: Topic :: Documentation
Classifier: Topic :: Software Development :: Documentation
Classifier: Topic :: Text Processing :: Markup :: Markdown
Requires-Python: >=3.8
Requires-Dist: requests>=2.31.0
